qurator_tsvtools-0.0.1-py3.7-nspkg.pth
qurator/tsvtools/__init__.py
qurator/tsvtools/cli.py
qurator/tsvtools/ocr.py
qurator/tsvtools/ocrd-tool.json
qurator/tsvtools/ocrd_cli.py
qurator/tsvtools/ocrd_processors.py
sbb_tools/__init__.py
sbb_tools/setup.py
sbb_tools/qurator/__init__.py
sbb_tools/qurator/bert/__init__.py
sbb_tools/qurator/bert/corpus.py
sbb_tools/qurator/bert/finetune_on_pregenerated.py
sbb_tools/qurator/bert/pregenerate_training_data.py
sbb_tools/qurator/sbb/__init__.py
sbb_tools/qurator/sbb/entropy.py
sbb_tools/qurator/sbb/language.py
sbb_tools/qurator/sbb/ned.py
sbb_tools/qurator/sbb/ner.py
sbb_tools/qurator/sbb/select.py
sbb_tools/qurator/sbb/xml.py
sbb_tools/qurator/topic_modeling/__init__.py
sbb_tools/qurator/topic_modeling/cli.py
sbb_tools/qurator/utils/__init__.py
sbb_tools/qurator/utils/csv.py
sbb_tools/qurator/utils/entities.py
sbb_tools/qurator/utils/ned.py
sbb_tools/qurator/utils/ner.py
sbb_tools/qurator/utils/parallel.py
sbb_tools/qurator/utils/parquet.py
sbb_tools/qurator/utils/pickle.py
sbb_tools/qurator/utils/qurator_data.py
sbb_tools/qurator/utils/tsv.py
sbb_tools/qurator/webapp/__init__.py
sbb_tools/qurator/webapp/app.py
sbb_tools/qurator/webapp/config.json
sbb_tools/qurator/webapp/wsgi.py
sbb_tools/qurator/wikidata/__init__.py
sbb_tools/qurator/wikidata/cli.py
sbb_tools/qurator/wikidata/entities.py
sbb_tools/qurator/wikipedia/__init__.py
sbb_tools/qurator/wikipedia/entities.py
sbb_tools/qurator/wikipedia/ned.py
sbb_tools/qurator/wikipedia/ner.py
sbb_tools/qurator/wikipedia/xml.py
tsvtools/__init__.py
tsvtools/cli.py
tsvtools/ocr.py
tsvtools/ocrd_cli.py
tsvtools/ocrd_processors.py
qurator_tsvtools-0.0.1.dist-info/LICENSE
qurator_tsvtools-0.0.1.dist-info/METADATA
qurator_tsvtools-0.0.1.dist-info/WHEEL
qurator_tsvtools-0.0.1.dist-info/entry_points.txt
qurator_tsvtools-0.0.1.dist-info/namespace_packages.txt
qurator_tsvtools-0.0.1.dist-info/top_level.txt
qurator_tsvtools-0.0.1.dist-info/RECORD
