Metadata-Version: 2.1
Name: qurator-tsvtools
Version: 0.0.1
Summary: Working with QURATOR TSV, especially for neat
Home-page: https://github.com/qurator-spk/neath
Author: Kai Labusch
Author-email: qurator@sbb.spk-berlin.de
License: Apache License 2.0
Keywords: qurator
Classifier: Intended Audience :: Science/Research
Classifier: License :: OSI Approved :: Apache Software License
Classifier: Programming Language :: Python :: 3
Classifier: Topic :: Scientific/Engineering :: Artificial Intelligence
Requires-Python: >=3.6.0
License-File: LICENSE
Requires-Dist: ocrd (>=2.23.2)
Requires-Dist: pandas
Requires-Dist: qurator-sbb-utils
